aaaaa_future_fstrings.pth
future_fstrings.py
future_fstrings-1.1.0.dist-info/LICENSE
future_fstrings-1.1.0.dist-info/METADATA
future_fstrings-1.1.0.dist-info/WHEEL
future_fstrings-1.1.0.dist-info/entry_points.txt
future_fstrings-1.1.0.dist-info/top_level.txt
future_fstrings-1.1.0.dist-info/RECORD
